m2secret/__init__.py
m2secret/tests/__init__.py
m2secret/tests/test_basic.py
m2secret_py3-1.3.dist-info/DESCRIPTION.rst
m2secret_py3-1.3.dist-info/METADATA
m2secret_py3-1.3.dist-info/RECORD
m2secret_py3-1.3.dist-info/WHEEL
m2secret_py3-1.3.dist-info/entry_points.txt
m2secret_py3-1.3.dist-info/metadata.json
m2secret_py3-1.3.dist-info/top_level.txt
